squadds/__init__.py
squadds/calcs/__init__.py
squadds/calcs/qubit.py
squadds/calcs/transmon_cross.py
squadds/components/__init__.py
squadds/components/cavity_claw.py
squadds/components/claw_coupler.py
squadds/components/coupled_systems.py
squadds/components/jjs.py
squadds/components/qubits.py
squadds/components/airbridge/__init__.py
squadds/components/airbridge/airbridge.py
squadds/components/airbridge/airbridge_generator.py
squadds/core/__init__.py
squadds/core/analysis.py
squadds/core/db.py
squadds/core/design_patterns.py
squadds/core/globals.py
squadds/core/metrics.py
squadds/core/processing.py
squadds/core/utils.py
squadds/database/HuggingFace.py
squadds/database/__init__.py
squadds/database/abstract_upload_data.py
squadds/database/checker.py
squadds/database/config.py
squadds/database/contributor.py
squadds/database/contributor_HF.py
squadds/database/github.py
squadds/database/new_contribution.py
squadds/database/utils.py
squadds/gds/__init__.py
squadds/gds/processing.py
squadds/interpolations/__init__.py
squadds/interpolations/interpolator.py
squadds/interpolations/physics.py
squadds/interpolations/utils.py
squadds/simulations/__init__.py
squadds/simulations/ansys_simulator.py
squadds/simulations/objects.py
squadds/simulations/simulator.py
squadds/simulations/sweeper_helperfunctions.py
squadds/simulations/utils.py
squadds/ui/__init__.py
squadds/ui/app.py
squadds/ui/utils_query.py
squadds-0.4.0.dist-info/METADATA
squadds-0.4.0.dist-info/WHEEL
squadds-0.4.0.dist-info/licenses/LICENSE
squadds-0.4.0.dist-info/RECORD
