Metadata-Version: 2.4
Name: SQuADDS
Version: 0.4.0
Summary: Open-source database of programmatically generated and experimentally validated superconducting quantum device designs, accessible through a user-friendly interface.
Project-URL: Homepage, https://github.com/LFL-Lab/SQuADDS
Project-URL: Documentation, https://lfl-lab.github.io/SQuADDS/
Project-URL: Repository, https://github.com/LFL-Lab/SQuADDS
Project-URL: Issues, https://github.com/LFL-Lab/SQuADDS/issues
Author-email: Sadman Ahmed Shanto <shanto@usc.edu>
License: MIT
License-File: LICENSE
Classifier: Development Status :: 4 - Beta
Classifier: Intended Audience :: Science/Research
Classifier: License :: OSI Approved :: MIT License
Classifier: Operating System :: OS Independent
Classifier: Programming Language :: Python :: 3
Classifier: Programming Language :: Python :: 3.10
Classifier: Programming Language :: Python :: 3.11
Classifier: Programming Language :: Python :: 3.12
Classifier: Topic :: Scientific/Engineering :: Physics
Requires-Python: >=3.10
Requires-Dist: datasets>=2.19
Requires-Dist: datashader>=0.16
Requires-Dist: gmsh>=4.15.0
Requires-Dist: huggingface-hub>=0.21
Requires-Dist: joblib>=1.3
Requires-Dist: matplotlib>=3.7
Requires-Dist: numba>=0.60
Requires-Dist: numpy<2.0,>=1.16.6
Requires-Dist: pandas>=1.5
Requires-Dist: plotly>=5.0
Requires-Dist: prettytable>=3.0
Requires-Dist: pyaedt>=0.6.46
Requires-Dist: pyepr-quantum>=0.8.5
Requires-Dist: pyside6>=6.10.1
Requires-Dist: python-dotenv>=1.0
Requires-Dist: quantum-metal>=0.5.0
Requires-Dist: requests>=2.32
Requires-Dist: scipy>=1.10
Requires-Dist: scqubits>=4.0
Requires-Dist: seaborn>=0.12
Requires-Dist: shapely>=2.0
Requires-Dist: streamlit>=1.45
Requires-Dist: tabulate>=0.9
Requires-Dist: tqdm>=4.0
Provides-Extra: all
Requires-Dist: gdspy>=1.6; extra == 'all'
Requires-Dist: gitpython>=3.1; extra == 'all'
Requires-Dist: jupyter-sphinx>=0.5; extra == 'all'
Requires-Dist: klayout>=0.29; extra == 'all'
Requires-Dist: myst-parser>=2.0; extra == 'all'
Requires-Dist: nbsphinx>=0.9; extra == 'all'
Requires-Dist: pre-commit>=4.5.1; extra == 'all'
Requires-Dist: pydata-sphinx-theme>=0.15; extra == 'all'
Requires-Dist: pygithub>=2.4; extra == 'all'
Requires-Dist: pytest-cov>=4.0; extra == 'all'
Requires-Dist: pytest>=8.0; extra == 'all'
Requires-Dist: qiskit-sphinx-theme; extra == 'all'
Requires-Dist: reno>=4.0; extra == 'all'
Requires-Dist: ruff>=0.14.11; extra == 'all'
Requires-Dist: sphinx-copybutton>=0.5; extra == 'all'
Requires-Dist: sphinx-design>=0.5; extra == 'all'
Requires-Dist: sphinx>=7.0; extra == 'all'
Requires-Dist: sphinxcontrib-katex>=0.9; extra == 'all'
Provides-Extra: contrib
Requires-Dist: gitpython>=3.1; extra == 'contrib'
Requires-Dist: pygithub>=2.4; extra == 'contrib'
Provides-Extra: dev
Requires-Dist: pre-commit>=4.5.1; extra == 'dev'
Requires-Dist: pytest-cov>=4.0; extra == 'dev'
Requires-Dist: pytest>=8.0; extra == 'dev'
Requires-Dist: ruff>=0.14.11; extra == 'dev'
Provides-Extra: docs
Requires-Dist: jupyter-sphinx>=0.5; extra == 'docs'
Requires-Dist: myst-parser>=2.0; extra == 'docs'
Requires-Dist: nbsphinx>=0.9; extra == 'docs'
Requires-Dist: pydata-sphinx-theme>=0.15; extra == 'docs'
Requires-Dist: qiskit-sphinx-theme; extra == 'docs'
Requires-Dist: reno>=4.0; extra == 'docs'
Requires-Dist: sphinx-copybutton>=0.5; extra == 'docs'
Requires-Dist: sphinx-design>=0.5; extra == 'docs'
Requires-Dist: sphinx>=7.0; extra == 'docs'
Requires-Dist: sphinxcontrib-katex>=0.9; extra == 'docs'
Provides-Extra: gds
Requires-Dist: gdspy>=1.6; extra == 'gds'
Requires-Dist: klayout>=0.29; extra == 'gds'
